openpartslibrary/__init__.py
openpartslibrary/cli.py
openpartslibrary/db.py
openpartslibrary/models.py
openpartslibrary-0.1.14.dist-info/licenses/LICENSE
openpartslibrary_flask/__init__.py
openpartslibrary_flask/forms.py
openpartslibrary-0.1.14.dist-info/METADATA
openpartslibrary-0.1.14.dist-info/WHEEL
openpartslibrary-0.1.14.dist-info/top_level.txt
openpartslibrary-0.1.14.dist-info/RECORD
