Metadata-Version: 2.4
Name: OpenPartsLibrary
Version: 0.1.14
Summary: Python library for creating a database of hardware components for manufacturing
Home-page: https://github.com/alekssadowski95/OpenPartsLibrary
Author: Aleksander Sadowski
Author-email: aleksander.sadowski@alsado.de
License: MIT
Classifier: Development Status :: 1 - Planning
Classifier: Intended Audience :: Science/Research
Classifier: License :: OSI Approved :: MIT License
Classifier: Programming Language :: Python :: 3
License-File: LICENSE
Requires-Dist: sqlalchemy
Requires-Dist: datetime
Requires-Dist: pandas
Requires-Dist: openpyxl
Dynamic: author
Dynamic: author-email
Dynamic: classifier
Dynamic: description
Dynamic: description-content-type
Dynamic: home-page
Dynamic: license
Dynamic: license-file
Dynamic: requires-dist
Dynamic: summary
